{
    "success":1,
    "errorCode":null,
    "message":"",
    "data":[{
        "id":"1","x":120.58537968270878,"y":28.0191978901138,"type":"type1","category":"category2","address":"鹿城区大南路交叉口停车场","allNum":"500","restNum":"100","img":"./images/jiankong.jpg"
    },{
        "id":"2","x":120.5856371747742,"y":27.994650313209505,"type":"type1","category":"category3","address":"鹿城区大南路交叉口停车场","allNum":"500","restNum":"100","img":"./images/jiankong.jpg"
    },{
        "id":"3","x":120.58750615579315,"y":28.00592602739603,"type":"type2","category":"category3","address":"鹿城区大南路交叉口停车场","allNum":"500","restNum":"100","img":"./images/jiankong.jpg"
    },{
        "id":"4","x":120.57963760951873,"y":28.007701405965136,"type":"type2","category":"category1","address":"鹿城区大南路交叉口停车场","allNum":"500","restNum":"100","img":"./images/jiankong.jpg"
    },{
        "id":"5","x":120.59955032924529,"y":28.01207877107744,"type":"type3","category":"category2","address":"鹿城区大南路交叉口停车场","allNum":"500","restNum":"100","img":"./images/jiankong.jpg"
    },{
        "id":"6","x":120.63763340611524,"y":28.008631059216796,"type":"type3","category":"category2","address":"鹿城区大南路交叉口停车场","allNum":"500","restNum":"100","img":"./images/jiankong.jpg"
    },{
        "id":"7","x":120.65531452794141,"y":28.007944413708984,"type":"type3","category":"category2","address":"鹿城区大南路交叉口停车场","allNum":"500","restNum":"100","img":"./images/jiankong.jpg"
    },{
        "id":"8","x":120.64020832676954,"y":27.994383164929687,"type":"type3","category":"category2","address":"鹿城区大南路交叉口停车场","allNum":"500","restNum":"100","img":"./images/jiankong.jpg"
    },{
        "id":"9","x":120.62647541661329,"y":27.96983558802539,"type":"type3","category":"category2","address":"鹿城区大南路交叉口停车场","allNum":"500","restNum":"100","img":"./images/jiankong.jpg"
    },{
        "id":"10","x":120.6901617874629,"y":28.013094255017577,"type":"type3","category":"category2","address":"鹿城区大南路交叉口停车场","allNum":"500","restNum":"100","img":"./images/jiankong.jpg"
    },{
        "id":"11","x":120.66200932164259,"y":27.979963609265624,"type":"type3","category":"category2","address":"鹿城区大南路交叉口停车场","allNum":"500","restNum":"100","img":"./images/jiankong.jpg"
    }]
  }